MANIFEST.in
README.md
setup.cfg
setup.py
versioneer.py
miniast/__init__.py
miniast/_version.py
miniast/base.py
miniast/source.py
miniast/util.py
miniast.egg-info/PKG-INFO
miniast.egg-info/SOURCES.txt
miniast.egg-info/dependency_links.txt
miniast.egg-info/top_level.txt