Metadata-Version: 1.0
Name: miniast
Version: 0.0.5
Summary: Lightweight macros for Python
Home-page: https://github.com/cpcloud/miniast
Author: Phillip Cloud
Author-email: cpcloud@gmail.com
License: Apache License, Version 2.0
Platform: UNKNOWN
